scrapy_freedb/__init__.py
scrapy_freedb/base.py
scrapy_freedb/plugin.py
scrapy_freedb/middleware/__init__.py
scrapy_freedb/middleware/dupefilter.py
scrapy_freedb/middleware/freedb.py
scrapy_freedb/middleware/mapper.py
scrapy_freedb/middleware/pipeline.py
scrapy_freedb-0.1.8.dist-info/METADATA
scrapy_freedb-0.1.8.dist-info/WHEEL
scrapy_freedb-0.1.8.dist-info/entry_points.txt
scrapy_freedb-0.1.8.dist-info/top_level.txt
scrapy_freedb-0.1.8.dist-info/RECORD
