Metadata-Version: 2.1
Name: scrapy-freedb
Version: 0.1.8
Summary: scrapy freedb plugin
Home-page: UNKNOWN
Author: UNKNOWN
Author-email: UNKNOWN
License: UNKNOWN
Platform: UNKNOWN
Requires-Dist: requests
